odoo/addons/account_banking_pain_base/README.rst
odoo/addons/account_banking_pain_base/__init__.py
odoo/addons/account_banking_pain_base/__manifest__.py
odoo/addons/account_banking_pain_base/post_install.py
odoo/addons/account_banking_pain_base/i18n/account_banking_pain_base.pot
odoo/addons/account_banking_pain_base/i18n/ca.po
odoo/addons/account_banking_pain_base/i18n/de.po
odoo/addons/account_banking_pain_base/i18n/es.po
odoo/addons/account_banking_pain_base/i18n/es_AR.po
odoo/addons/account_banking_pain_base/i18n/fr.po
odoo/addons/account_banking_pain_base/i18n/hr.po
odoo/addons/account_banking_pain_base/i18n/it.po
odoo/addons/account_banking_pain_base/i18n/nb_NO.po
odoo/addons/account_banking_pain_base/i18n/nl.po
odoo/addons/account_banking_pain_base/i18n/pt_BR.po
odoo/addons/account_banking_pain_base/i18n/sk.po
odoo/addons/account_banking_pain_base/i18n/sl.po
odoo/addons/account_banking_pain_base/models/__init__.py
odoo/addons/account_banking_pain_base/models/account_payment_line.py
odoo/addons/account_banking_pain_base/models/account_payment_method.py
odoo/addons/account_banking_pain_base/models/account_payment_mode.py
odoo/addons/account_banking_pain_base/models/account_payment_order.py
odoo/addons/account_banking_pain_base/models/bank_payment_line.py
odoo/addons/account_banking_pain_base/models/res_bank.py
odoo/addons/account_banking_pain_base/models/res_company.py
odoo/addons/account_banking_pain_base/models/res_config_settings.py
odoo/addons/account_banking_pain_base/readme/CONFIGURE.rst
odoo/addons/account_banking_pain_base/readme/CONTRIBUTORS.rst
odoo/addons/account_banking_pain_base/readme/DESCRIPTION.rst
odoo/addons/account_banking_pain_base/readme/INSTALL.rst
odoo/addons/account_banking_pain_base/readme/USAGE.rst
odoo/addons/account_banking_pain_base/security/security.xml
odoo/addons/account_banking_pain_base/static/description/icon.png
odoo/addons/account_banking_pain_base/static/description/index.html
odoo13_addon_account_banking_pain_base-13.0.1.0.3.dist-info/METADATA
odoo13_addon_account_banking_pain_base-13.0.1.0.3.dist-info/WHEEL
odoo13_addon_account_banking_pain_base-13.0.1.0.3.dist-info/top_level.txt
odoo13_addon_account_banking_pain_base-13.0.1.0.3.dist-info/RECORD
