Metadata-Version: 2.1
Name: odoo13-addon-account-banking-pain-base
Version: 13.0.1.0.3
Summary: Base module for PAIN file generation
Home-page: https://github.com/OCA/bank-payment
Author: Akretion, Noviat, Tecnativa, Odoo Community Association (OCA)
Author-email: support@odoo-community.org
License: AGPL-3
Platform: UNKNOWN
Classifier: Programming Language :: Python
Classifier: Framework :: Odoo
Classifier: Framework :: Odoo :: 13.0
Classifier: License :: OSI Approved :: GNU Affero General Public License v3
Requires-Python: >=3.5
Requires-Dist: lxml
Requires-Dist: odoo13-addon-account-payment-order
Requires-Dist: odoo (<13.1dev,>=13.0a)
Requires-Dist: unidecode
